README.rst
setup.cfg
setup.py
flask_ffs/__init__.py
flask_ffs/ffs_mixin.py
flask_ffs/tests.py
flask_ffs.egg-info/PKG-INFO
flask_ffs.egg-info/SOURCES.txt
flask_ffs.egg-info/dependency_links.txt
flask_ffs.egg-info/requires.txt
flask_ffs.egg-info/top_level.txt